Adyan/__init__.py
Adyan/headers.py
Adyan/connenct/__init__.py
Adyan/connenct/mongo_connect.py
Adyan/connenct/mysql_connect.py
Adyan/connenct/rabbit_connect.py
Adyan/connenct/redis_connect.py
Adyan-0.0.2.dist-info/LICENSE
Adyan-0.0.2.dist-info/METADATA
Adyan-0.0.2.dist-info/WHEEL
Adyan-0.0.2.dist-info/top_level.txt
Adyan-0.0.2.dist-info/RECORD
